czneau/__init__.py
czneau/__main__.py
czneau/analyse.py
czneau/czneau.py
czneau/refer.py
czneau-2.0.0.dist-info/LICENSE
czneau-2.0.0.dist-info/METADATA
czneau-2.0.0.dist-info/WHEEL
czneau-2.0.0.dist-info/entry_points.txt
czneau-2.0.0.dist-info/top_level.txt
czneau-2.0.0.dist-info/RECORD
