Metadata-Version: 2.1
Name: czneau
Version: 2.0.0
Summary: 东北农业大学数据抓取
Home-page: https://github.com/U-73A5/ChizZaiDongNongWD
Author: U-73A5
Author-email: u73a5@foxmail.com
License: MIT
Classifier: Programming Language :: Python :: 3
Requires-Python: >=3.7.0
License-File: LICENSE
Requires-Dist: importlib-metadata
Requires-Dist: requests
Requires-Dist: rich
